{"title":"Предисловие","markdown":{"headingText":"Предисловие","headingAttr":{"id":"","classes":["unnumbered"],"keyvalue":[]},"containsRefs":false,"markdown":"\nОсновная цель книги --- показать, как можно интерпретировать задачи, рассматриваемые в различных вопросах ..., с помощью современных алгоритмов и программных средств, а также каким образом можно анализировать модели на основе сложно организованных данных. Подход, который рассмотрен в книге --- это ситуационное исследование, основанное на конкретных примерах. При этом, в книге будут не только рассмотрены различные методы анализа, но и их практическое применение. Несмотря на то, что набор методов для решения тех или иных задач анализа данных является во многом стандартным, каждое исследование по-своему уникально и использует свои инструменты. Область исследования затронутая в книге огромна, данное издание не претендует на полноту, а является введением в современный анализ данных.\n\n## Типографские соглашения\n\n*Курсив* будет использоваться для обозначения новых терминов и определений.\n\n:::{.callout-important}\n## Важно\n\nЭтот элемент будет использоваться для важных замечаний и предостережений.\n:::\n\n:::{.callout-tip}\n## Совет\n\nЭтот элемент будет использоваться для рекомендаций и советов.\n:::\n\n```{.r}\nЭтот блок будет использоваться для обозначения кода.\n```\n\n:::{.callout-note collapse=\"true\" icon=false}\n## Код (пример)\n\n```{.r}\nРазвертывающийся блок для обозначения кода большого объема.\n```\n\n:::\n\n## Благодарности\n\nАвтор выражает благодарность ... за помощь в написании книги и поддержку.","srcMarkdownNoYaml":""},"formats":{"html":{"identifier":{"display-name":"HTML","target-format":"html","base-format":"html"},"execute":{"fig-width":7,"fig-height":5,"fig-format":"retina","fig-dpi":96,"df-print":"default","error":false,"eval":true,"cache":true,"freeze":false,"echo":true,"output":true,"warning":true,"include":true,"keep-md":false,"keep-ipynb":false,"ipynb":null,"enabled":null,"daemon":null,"daemon-restart":false,"debug":false,"ipynb-filters":[],"execute_notebooks":"force","allow_errors":true,"engine":"markdown"},"render":{"keep-tex":false,"keep-source":false,"keep-hidden":false,"prefer-html":false,"output-divs":true,"output-ext":"html","fig-align":"default","fig-pos":null,"fig-env":null,"code-fold":false,"code-overflow":"scroll","code-link":false,"code-line-numbers":false,"code-tools":false,"tbl-colwidths":"auto","merge-includes":true,"latex-auto-mk":true,"latex-auto-install":true,"latex-clean":true,"latex-max-runs":10,"latex-makeindex":"makeindex","latex-makeindex-opts":[],"latex-tlmgr-opts":[],"latex-input-paths":[],"latex-output-dir":null,"link-external-icon":false,"link-external-newwindow":false,"self-contained-math":false,"format-resources":[],"notebook-links":true,"format-links":true},"pandoc":{"standalone":true,"wrap":"none","default-image-extension":"png","to":"html","highlight-style":"ally","reference-location":"margin","toc":true,"output-file":"index.html"},"language":{"crossref-apx-prefix":"Приложение","title-block-affiliation-single":"Организация"},"metadata":{"lang":"ru","fig-responsive":true,"quarto-version":"1.3.228","bibliography":["references.bib"],"csl":"gost-r-7-0-5-2008-numeric.csl","crossref":{"appendix-title":"Приложение","appendix-delim":":"},"citation":{"url":"https://quarto-meetup-begin-book.netlify.app"},"theme":{"light":["flatly","theme.scss"],"dark":["darkly","theme.scss"]}},"extensions":{"book":{"multiFile":true}}}}}